perception.py
perception_nassir-0.1.2.dist-info/LICENSE.txt
perception_nassir-0.1.2.dist-info/METADATA
perception_nassir-0.1.2.dist-info/WHEEL
perception_nassir-0.1.2.dist-info/top_level.txt
perception_nassir-0.1.2.dist-info/RECORD
