Metadata-Version: 2.1
Name: perception-nassir
Version: 0.1.2
Summary: A method for detecting anomalies in univariate and multivariate data
Home-page: https://github.com/M-Nassir/perception
Author: Nassir Mohammad
Classifier: Programming Language :: Python :: 3
Classifier: License :: OSI Approved :: BSD License
Classifier: Operating System :: OS Independent
Requires-Python: >=3.6
License-File: LICENSE.txt
Requires-Dist: numpy
Requires-Dist: scipy
